telegram_code_sender/__init__.py
telegram_code_sender/telegram_code_sender.py
telegram_code_sender-1.0.0.dist-info/licenses/LICENSE
telegram_code_sender-1.0.0.dist-info/METADATA
telegram_code_sender-1.0.0.dist-info/WHEEL
telegram_code_sender-1.0.0.dist-info/top_level.txt
telegram_code_sender-1.0.0.dist-info/RECORD
