Metadata-Version: 2.4
Name: telegram-code-sender
Version: 1.0.0
Summary: 一个简单的工具，用于将Python代码文件自动发送到Telegram机器人
Home-page: 
Author: Your Name
Author-email: Your Name <your.email@example.com>
License: MIT
Project-URL: Homepage, https://github.com/yourusername/telegram-code-sender
Project-URL: Bug Reports, https://github.com/yourusername/telegram-code-sender/issues
Project-URL: Source, https://github.com/yourusername/telegram-code-sender
Keywords: telegram,bot,code,sender,automation,developer-tools
Classifier: Development Status :: 4 - Beta
Classifier: Intended Audience :: Developers
Classifier: License :: OSI Approved :: MIT License
Classifier: Operating System :: OS Independent
Classifier: Programming Language :: Python :: 3
Classifier: Programming Language :: Python :: 3.7
Classifier: Programming Language :: Python :: 3.8
Classifier: Programming Language :: Python :: 3.9
Classifier: Programming Language :: Python :: 3.10
Classifier: Programming Language :: Python :: 3.11
Classifier: Topic :: Communications :: Chat
Classifier: Topic :: Software Development :: Libraries :: Python Modules
Classifier: Topic :: Utilities
Requires-Python: >=3.7
License-File: LICENSE
Requires-Dist: requests
Dynamic: author
Dynamic: license-file
Dynamic: requires-python
